Metadata-Version: 2.1
Name: pytrips
Version: 0.5.22
Summary: A simple python package for accessing the trips ontology and lexicon
Home-page: https://github.com/mrmechko/pytrips
Author: Rik Bose
Author-email: rbose@cs.rochester.edu
License: UNKNOWN
Platform: UNKNOWN
Classifier: Programming Language :: Python :: 3
Classifier: License :: OSI Approved :: GNU General Public License v2 or later (GPLv2+)
Classifier: Operating System :: OS Independent
Requires-Dist: nltk
Requires-Dist: thesoulshell (>=0.0.2)
Requires-Dist: jsontrips (>=0.1.34)
Requires-Dist: graphviz
Requires-Dist: anytree
Provides-Extra: tools
Requires-Dist: spacy (<3.0.0,>=2.0.0) ; extra == 'tools'
Requires-Dist: en-core-web-lg (==2.1.0) ; extra == 'tools'
